randospanish/randospanish.py
randospanish/utils.py
randospanish/data/spanish_database_5000words.npy
randospanish/data/spanish_database_5000words.txt
randospanish-1.0.0.dist-info/LICENSE
randospanish-1.0.0.dist-info/METADATA
randospanish-1.0.0.dist-info/WHEEL
randospanish-1.0.0.dist-info/top_level.txt
randospanish-1.0.0.dist-info/RECORD
