Metadata-Version: 2.1
Name: randospanish
Version: 1.0.0
Summary: Spanish learning app
Home-page: https://github.com/dnidever/randospanish
Author: David Nidever
Author-email: dnidever@montana.edu
License: MIT
Requires: numpy
Requires: dlnpyutils
Requires-Python: >=3.6
License-File: LICENSE
Requires-Dist: astropy
Requires-Dist: scipy
Provides-Extra: docs
Requires-Dist: sphinx ; extra == 'docs'
Requires-Dist: sphinx-astropy ; extra == 'docs'
Requires-Dist: nbsphinx ; extra == 'docs'
Requires-Dist: nbconvert ; extra == 'docs'
Requires-Dist: nbformat ; extra == 'docs'
Requires-Dist: ipykernel ; extra == 'docs'
Provides-Extra: test
Requires-Dist: pytest ; extra == 'test'
Requires-Dist: pytest-astropy ; extra == 'test'
Requires-Dist: ipython ; extra == 'test'
